bilidown/__init__.py
bilidown/__main__.py
BiliDown-1.2.3.dist-info/LICENSE
BiliDown-1.2.3.dist-info/METADATA
BiliDown-1.2.3.dist-info/WHEEL
BiliDown-1.2.3.dist-info/entry_points.txt
BiliDown-1.2.3.dist-info/top_level.txt
BiliDown-1.2.3.dist-info/RECORD
