Metadata-Version: 2.1
Name: BiliDown
Version: 1.2.3
Summary: 哔哩哔哩命令行下载器
Home-page: https://github.com/nemo2011/BiliDown
Author: Nemo2011
License: GPLv3+
Keywords: bilibili,download,api
Classifier: License :: OSI Approved :: GNU General Public License v3 or later (GPLv3+)
Classifier: Natural Language :: Chinese (Simplified)
Classifier: Programming Language :: Python :: 3.8
Classifier: Programming Language :: Python :: 3.9
Classifier: Programming Language :: Python :: 3.10
Requires-Python: >=3.8
License-File: LICENSE
Requires-Dist: keyboard
Requires-Dist: bilibili-api-python (>=15.3.1)
Requires-Dist: colorama
